meta_prompt_generator/__init__.py
meta_prompt_generator/cli.py
meta_prompt_generator/generator.py
meta_prompt_generator/prompts.py
meta_prompt_generator/utils.py
meta_prompt_generator-0.1.5.dist-info/LICENSE.txt
meta_prompt_generator-0.1.5.dist-info/METADATA
meta_prompt_generator-0.1.5.dist-info/WHEEL
meta_prompt_generator-0.1.5.dist-info/entry_points.txt
meta_prompt_generator-0.1.5.dist-info/top_level.txt
meta_prompt_generator-0.1.5.dist-info/RECORD
