Metadata-Version: 2.1
Name: meta-prompt-generator
Version: 0.1.5
Summary: A package to generate step-by-step reasoning prompts for language models
Home-page: https://github.com/Zakk-Yang/meta-prompt-generator.git
Author: Zakk Yang
Author-email: zakkyang@hotmail.com
Classifier: Development Status :: 3 - Alpha
Classifier: Intended Audience :: Developers
Classifier: License :: OSI Approved :: MIT License
Classifier: Operating System :: OS Independent
Classifier: Programming Language :: Python :: 3
Classifier: Programming Language :: Python :: 3.7
Classifier: Programming Language :: Python :: 3.8
Classifier: Programming Language :: Python :: 3.9
Classifier: Programming Language :: Python :: 3.10
Requires-Python: >=3.7
License-File: LICENSE.txt
Requires-Dist: openai
Requires-Dist: python-dotenv
